ctfd_sdk/__init__.py
ctfd_sdk/api.py
ctfd_sdk/settings.py
ctfd_sdk-0.2.2.dist-info/WHEEL
ctfd_sdk-0.2.2.dist-info/METADATA
ctfd_sdk-0.2.2.dist-info/RECORD
